README.rst
setup.py
vcloudtools/__init__.py
vcloudtools/api.py
vcloudtools/vcloud.py
vcloudtools.egg-info/PKG-INFO
vcloudtools.egg-info/SOURCES.txt
vcloudtools.egg-info/dependency_links.txt
vcloudtools.egg-info/entry_points.txt
vcloudtools.egg-info/requires.txt
vcloudtools.egg-info/top_level.txt
vcloudtools/command/__init__.py
vcloudtools/command/browse.py
vcloudtools/command/login.py
vcloudtools/command/org.py