Metadata-Version: 1.0
Name: vcloudtools
Version: 0.0.1
Summary: vCloud: tools for interacting with the vCloud API
Home-page: https://github.com/alphagov/vcloudtools
Author: Government Digital Service
Author-email: nick@whiteink.com
License: MIT
Keywords: sysadmin vcloud vmware virtualisation api
Platform: UNKNOWN
